rest_hooks/__init__.py
rest_hooks/admin.py
rest_hooks/apps.py
rest_hooks/client.py
rest_hooks/config.py
rest_hooks/models.py
rest_hooks/signals.py
rest_hooks/tasks.py
rest_hooks/tests.py
rest_hooks/utils.py
rest_hooks/migrations/0001_initial.py
rest_hooks/migrations/0002_swappable_hook_model.py
rest_hooks/migrations/__init__.py
rest_hooks-0.1.0.dist-info/AUTHORS.md
rest_hooks-0.1.0.dist-info/LICENSE.md
rest_hooks-0.1.0.dist-info/METADATA
rest_hooks-0.1.0.dist-info/WHEEL
rest_hooks-0.1.0.dist-info/top_level.txt
rest_hooks-0.1.0.dist-info/RECORD
